{
    "Ar36": {
        "error": 0.0036426695119343355,
        "error_type": "SEM",
        "filter_outliers_dict": {
            "filter_outliers": true,
            "iterations": 1,
            "std_devs": 2,
            "use_iqr_filtering": false,
            "use_standard_deviation_filtering": false
        },
        "fit": "Parabolic",
        "fn": 269,
        "include_baseline_error": false,
        "n": 280,
        "outlier_excluded": [
            64,
            163,
            196,
            227,
            135,
            167,
            106,
            46,
            112,
            57,
            62
        ],
        "reviewed": true,
        "user_excluded": [],
        "value": 1.898607300604384
    },
    "Ar37": {
        "error": 0.047935588508501735,
        "error_type": "SEM",
        "filter_outliers_dict": {
            "filter_outliers": true,
            "iterations": 1,
            "std_devs": 2,
            "use_iqr_filtering": false,
            "use_standard_deviation_filtering": false
        },
        "fit": "Linear",
        "fn": 272,
        "include_baseline_error": false,
        "n": 280,
        "outlier_excluded": [
            0,
            1,
            193,
            139,
            276,
            245,
            22,
            159
        ],
        "reviewed": true,
        "user_excluded": [],
        "value": 688.2356163996014
    },
    "Ar38": {
        "error": 0.0033040137305982735,
        "error_type": "SEM",
        "filter_outliers_dict": {
            "filter_outliers": true,
            "iterations": 1,
            "std_devs": 2,
            "use_iqr_filtering": false,
            "use_standard_deviation_filtering": false
        },
        "fit": "Linear",
        "fn": 269,
        "include_baseline_error": false,
        "n": 280,
        "outlier_excluded": [
            192,
            2,
            100,
            263,
            232,
            173,
            175,
            21,
            22,
            214,
            278
        ],
        "reviewed": true,
        "user_excluded": [],
        "value": 0.5488549730929257
    },
    "Ar39": {
        "error": 0.013394424368447361,
        "error_type": "SEM",
        "filter_outliers_dict": {
            "filter_outliers": true,
            "iterations": 1,
            "std_devs": 2,
            "use_iqr_filtering": false,
            "use_standard_deviation_filtering": false
        },
        "fit": "Parabolic",
        "fn": 270,
        "include_baseline_error": false,
        "n": 280,
        "outlier_excluded": [
            259,
            5,
            102,
            101,
            107,
            13,
            19,
            180,
            58,
            253
        ],
        "reviewed": true,
        "user_excluded": [],
        "value": 4.413963111461728
    },
    "Ar40": {
        "error": 0.015264488167871185,
        "error_type": "SEM",
        "filter_outliers_dict": {
            "filter_outliers": true,
            "iterations": 1,
            "std_devs": 2,
            "use_iqr_filtering": false,
            "use_standard_deviation_filtering": false
        },
        "fit": "Parabolic",
        "fn": 268,
        "include_baseline_error": false,
        "n": 280,
        "outlier_excluded": [
            228,
            260,
            102,
            230,
            42,
            110,
            49,
            52,
            120,
            152,
            153,
            30
        ],
        "reviewed": true,
        "user_excluded": [],
        "value": 45.69610294136815
    },
    "Ar41": {
        "error": 0.0025432212106910337,
        "error_type": "SEM",
        "filter_outliers_dict": {
            "filter_outliers": true,
            "iterations": 1,
            "std_devs": 2
        },
        "fit": "linear",
        "value": 0.003716656166826423
    }
}