{
    "Ar36": {
        "error": 0.000906189151034919,
        "error_type": "SEM",
        "filter_outliers_dict": {
            "filter_outliers": true,
            "iterations": 2,
            "std_devs": 2,
            "use_iqr_filtering": false,
            "use_standard_deviation_filtering": false
        },
        "fit": "linear",
        "fn": 314,
        "include_baseline_error": true,
        "n": 340,
        "outlier_excluded": [
            5,
            261,
            156,
            157,
            34,
            36,
            293,
            296,
            306,
            54,
            187,
            315,
            71,
            331,
            207,
            86,
            88,
            91,
            92,
            233,
            106,
            235,
            236,
            243,
            245,
            247
        ],
        "reviewed": true,
        "user_excluded": [],
        "value": 0.45689243350828895
    },
    "Ar37": {
        "error": 0.031921847648112074,
        "error_type": "SEM",
        "filter_outliers_dict": {
            "filter_outliers": true,
            "iterations": 2,
            "std_devs": 2,
            "use_iqr_filtering": false,
            "use_standard_deviation_filtering": false
        },
        "fit": "linear",
        "fn": 314,
        "include_baseline_error": true,
        "n": 340,
        "outlier_excluded": [
            130,
            8,
            137,
            14,
            15,
            16,
            18,
            277,
            176,
            306,
            188,
            61,
            63,
            66,
            323,
            324,
            325,
            326,
            330,
            84,
            85,
            92,
            93,
            225,
            106,
            118
        ],
        "reviewed": true,
        "user_excluded": [],
        "value": 596.1866332423865
    },
    "Ar38": {
        "error": 0.00047151793328140113,
        "error_type": "SEM",
        "filter_outliers_dict": {
            "filter_outliers": true,
            "iterations": 2,
            "std_devs": 2,
            "use_iqr_filtering": false,
            "use_standard_deviation_filtering": false
        },
        "fit": "linear",
        "fn": 311,
        "include_baseline_error": true,
        "n": 340,
        "outlier_excluded": [
            1,
            130,
            137,
            266,
            138,
            12,
            142,
            272,
            147,
            275,
            150,
            282,
            288,
            291,
            313,
            64,
            321,
            322,
            332,
            80,
            212,
            214,
            220,
            97,
            225,
            100,
            104,
            241,
            255
        ],
        "reviewed": true,
        "user_excluded": [],
        "value": 0.10234037853712794
    },
    "Ar39": {
        "error": 0.0067074248060280724,
        "error_type": "SEM",
        "filter_outliers_dict": {
            "filter_outliers": true,
            "iterations": 2,
            "std_devs": 2,
            "use_iqr_filtering": false,
            "use_standard_deviation_filtering": false
        },
        "fit": "linear",
        "fn": 314,
        "include_baseline_error": true,
        "n": 340,
        "outlier_excluded": [
            143,
            271,
            280,
            283,
            159,
            34,
            163,
            298,
            301,
            48,
            176,
            56,
            185,
            315,
            68,
            197,
            328,
            333,
            79,
            336,
            90,
            97,
            102,
            119,
            250,
            255
        ],
        "reviewed": true,
        "user_excluded": [],
        "value": 0.9858202275883902
    },
    "Ar40": {
        "error": 0.029611484357615972,
        "error_type": "SEM",
        "filter_outliers_dict": {
            "filter_outliers": true,
            "iterations": 2,
            "std_devs": 2,
            "use_iqr_filtering": false,
            "use_standard_deviation_filtering": false
        },
        "fit": "parabolic",
        "fn": 314,
        "include_baseline_error": true,
        "n": 340,
        "outlier_excluded": [
            129,
            8,
            141,
            148,
            277,
            24,
            283,
            51,
            311,
            57,
            62,
            66,
            324,
            325,
            326,
            331,
            76,
            332,
            206,
            333,
            96,
            108,
            109,
            237,
            241,
            244
        ],
        "reviewed": true,
        "user_excluded": [],
        "value": 24.621696438326214
    }
}