{
    "AX": {
        "error": 1e-20,
        "fit": "default",
        "references": [],
        "value": 1.0
    },
    "H1": {
        "error": 0.0002326865984735048,
        "fit": "Weighted Mean",
        "reference_data": {
            "es": [
                0.0006238169636117653,
                0.0006321636675935192,
                0.0006173491282821493,
                0.0006193017957926145,
                0.0006342367219524143,
                0.0006217552619887163,
                0.0006139925700055124,
                0.0005828828217274898
            ],
            "vs": [
                1.0004918633855495,
                0.9985803007707675,
                1.0006094083012258,
                1.001102261223873,
                1.0008927771988472,
                1.00057395811622,
                1.0006716373774858,
                1.0003524525408476
            ],
            "xs": [
                1673806465.0,
                1673807060.0,
                1673812626.0,
                1673813222.0,
                1673833015.0,
                1673855785.0,
                1673872232.0,
                1673895042.0
            ]
        },
        "reference_detector": "rad40",
        "references": [
            {
                "exclude": "ok",
                "record_id": "c-03-F-1882",
                "uuid": "cc5322da-bdfc-44a4-b917-bbf3c573ac1a"
            },
            {
                "exclude": "omit",
                "record_id": "c-03-F-1883",
                "uuid": "0f54641b-8747-45ef-9390-30a7a1bab732"
            },
            {
                "exclude": "ok",
                "record_id": "c-03-F-1884",
                "uuid": "958d6b56-3637-4170-97b6-f4bd505a7c03"
            },
            {
                "exclude": "ok",
                "record_id": "c-03-F-1885",
                "uuid": "313d1389-1c65-42e6-8b34-94e99736711f"
            },
            {
                "exclude": "ok",
                "record_id": "c-03-F-1886",
                "uuid": "f4a09a12-303c-4647-afe6-743cbedd49a5"
            },
            {
                "exclude": "ok",
                "record_id": "c-03-F-1887",
                "uuid": "08bd1ec9-bca0-4b50-876b-da795f48c72d"
            },
            {
                "exclude": "ok",
                "record_id": "c-03-F-1888",
                "uuid": "5e70fb64-2dff-4a5b-a513-a94c0836a062"
            },
            {
                "exclude": "ok",
                "record_id": "c-03-F-1889",
                "uuid": "e06c6e5b-fe34-44a0-8d63-a2987ca9c4bd"
            }
        ],
        "reviewed": true,
        "standard_ratio": 6.600975,
        "value": 1.0006637941300804
    },
    "H2": {
        "coefficients": [
            9e-10,
            -1e-05,
            1.0154
        ],
        "error": 4.4987536619846297e-07,
        "fit": "bulk_edit",
        "reference_data": null,
        "reference_detector": "H2",
        "references": "",
        "reviewed": true,
        "scaling_value": 70.48598854402687,
        "standard_ratio": null,
        "value": 1.0146996115616826,
        "variable": "Ar40"
    },
    "L1": {
        "error": 1e-20,
        "fit": "default",
        "references": [],
        "value": 1.0
    },
    "L2(CDD)": {
        "coefficients": [
            9e-10,
            -1e-05,
            1.0154
        ],
        "error": 4.4987536619846297e-07,
        "fit": "bulk_edit",
        "reference_data": null,
        "reference_detector": "L2(CDD)",
        "references": "",
        "reviewed": true,
        "scaling_value": 70.48598854402687,
        "standard_ratio": null,
        "value": 1.0146996115616826,
        "variable": "Ar40"
    }
}