{
    "Ar36": {
        "error": 0.0048535473911385674, 
        "fit": "Parabolic", 
        "value": 4.36333605757853
    }, 
    "Ar37": {
        "error": 0.01381709460292603, 
        "fit": "linear", 
        "value": -0.010707095136929065
    }, 
    "Ar38": {
        "error": 0.018026025771932845, 
        "fit": "linear", 
        "value": 1.309242411945279
    }, 
    "Ar39": {
        "error": 0.026086627750183323, 
        "fit": "Parabolic", 
        "value": 0.08814245603248978
    }, 
    "Ar40": {
        "error": 0.11723078896998251, 
        "fit": "Parabolic", 
        "value": 1358.5476438373275
    }
}